jtlocalize/__init__.py
jtlocalize/genstrings.py
jtlocalize/merge_translations.py
jtlocalize/mock_translate.py
jtlocalize/prepare_for_translation.py
jtlocalize/word_count.py
jtlocalize/configuration/__init__.py
jtlocalize/configuration/localization_configuration.py
jtlocalize/core/__init__.py
jtlocalize/core/add_genstrings_comments_to_file.py
jtlocalize/core/create_localized_strings_from_ib_files.py
jtlocalize/core/handle_duplicates_in_localization.py
jtlocalize/core/localization_commandline_operation.py
jtlocalize/core/localization_diff.py
jtlocalize/core/localization_merge_back.py
jtlocalize/core/localization_objects.py
jtlocalize/core/localization_utils.py
jtlocalize/core/merge_strings_files.py
jtlocalize-1.0.0.data/scripts/jtlocalize
jtlocalize-1.0.0.dist-info/LICENSE
jtlocalize-1.0.0.dist-info/METADATA
jtlocalize-1.0.0.dist-info/WHEEL
jtlocalize-1.0.0.dist-info/top_level.txt
jtlocalize-1.0.0.dist-info/RECORD
