Metadata-Version: 2.1
Name: jtlocalize
Version: 1.0.0
Summary: iOS localization framework
Home-page: https://github.com/joytunes/JTLocalize/
Author: JoyTunes
Author-email: info@joytunes.com
License: MIT
Platform: UNKNOWN
